Metadata-Version: 2.1
Name: tslite
Version: 1.0.4
Summary: A Simple Time Series Database Implemented By Python.
Home-page: https://github.com/sintrb/tslite/
Author: trb
Author-email: sintrb@gmail.com
License: UNKNOWN
Keywords: TSDB,tslite,Time Series Database
Platform: UNKNOWN
